deus_llm_token_stats_guru/__init__.py
deus_llm_token_stats_guru/__main__.py
deus_llm_token_stats_guru/_exceptions.py
deus_llm_token_stats_guru/_logging.py
deus_llm_token_stats_guru/cli.py
deus_llm_token_stats_guru/core.py
deus_llm_token_stats_guru/document_processor.py
deus_llm_token_stats_guru/py.typed
deus_llm_token_stats_guru/processors/__init__.py
deus_llm_token_stats_guru/processors/base.py
deus_llm_token_stats_guru/processors/csv_processor.py
deus_llm_token_stats_guru/processors/docx_processor.py
deus_llm_token_stats_guru/processors/html_processor.py
deus_llm_token_stats_guru/processors/json_processor.py
deus_llm_token_stats_guru/processors/opendocument_processor.py
deus_llm_token_stats_guru/processors/pdf_processor.py
deus_llm_token_stats_guru/processors/pptx_processor.py
deus_llm_token_stats_guru/processors/rtf_processor.py
deus_llm_token_stats_guru/processors/text_processor.py
deus_llm_token_stats_guru/processors/xlsx_processor.py
deus_llm_token_stats_guru/types/__init__.py
deus_llm_token_stats_guru/types/result_types.py
deus_llm_token_stats_guru-0.3.3.dist-info/LICENSE
deus_llm_token_stats_guru-0.3.3.dist-info/METADATA
deus_llm_token_stats_guru-0.3.3.dist-info/WHEEL
deus_llm_token_stats_guru-0.3.3.dist-info/entry_points.txt
deus_llm_token_stats_guru-0.3.3.dist-info/top_level.txt
deus_llm_token_stats_guru-0.3.3.dist-info/RECORD
