Metadata-Version: 2.1
Name: deus-llm-token-stats-guru
Version: 0.3.3
Summary: Advanced LLM token analysis and statistics toolkit for various data formats
Home-page: https://github.com/yourusername/deus-llm-token-stats-guru
Author: deus-global
Author-email: sean@deus.com.tw
License: UNKNOWN
Project-URL: Bug Tracker, https://github.com/yourusername/deus-llm-token-stats-guru/issues
Project-URL: Repository, https://github.com/yourusername/deus-llm-token-stats-guru.git
Keywords: llm tokens tiktoken csv analysis statistics
Platform: UNKNOWN
Classifier: Development Status :: 4 - Beta
Classifier: Intended Audience :: Developers
Classifier: Intended Audience :: Science/Research
Classifier: License :: OSI Approved :: MIT License
Classifier: Programming Language :: Python :: 3
Classifier: Programming Language :: Python :: 3.10
Classifier: Programming Language :: Python :: 3.11
Classifier: Programming Language :: Python :: 3.12
Classifier: Topic :: Text Processing
Classifier: Topic :: Scientific/Engineering :: Information Analysis
Requires-Python: >=3.10
Requires-Dist: tiktoken (>=0.5.0)
Requires-Dist: click (>=8.0.0)
Requires-Dist: pandas (>=2.0.0)
Provides-Extra: all
Requires-Dist: PyMuPDF (>=1.21.0) ; extra == 'all'
Requires-Dist: PyPDF2 (>=3.0.0) ; extra == 'all'
Requires-Dist: pdfplumber (>=0.7.0) ; extra == 'all'
Requires-Dist: python-docx (>=0.8.11) ; extra == 'all'
Requires-Dist: docx2txt (>=0.8) ; extra == 'all'
Requires-Dist: openpyxl (>=3.0.0) ; extra == 'all'
Requires-Dist: xlrd (>=2.0.0) ; extra == 'all'
Requires-Dist: python-pptx (>=0.6.0) ; extra == 'all'
Requires-Dist: odfpy (>=1.4.0) ; extra == 'all'
Requires-Dist: striprtf (>=0.0.10) ; extra == 'all'
Requires-Dist: beautifulsoup4 (>=4.9.0) ; extra == 'all'
Requires-Dist: lxml (>=4.6.0) ; extra == 'all'
Provides-Extra: dev
Requires-Dist: pytest (>=7.0.0) ; extra == 'dev'
Requires-Dist: pytest-cov (>=4.0.0) ; extra == 'dev'
Requires-Dist: mypy (>=1.0.0) ; extra == 'dev'
Requires-Dist: ruff (>=0.1.0) ; extra == 'dev'
Requires-Dist: build (>=0.10.0) ; extra == 'dev'
Requires-Dist: twine (>=4.0.0) ; extra == 'dev'
Provides-Extra: docx
Requires-Dist: python-docx (>=0.8.11) ; extra == 'docx'
Requires-Dist: docx2txt (>=0.8) ; extra == 'docx'
Provides-Extra: excel
Requires-Dist: openpyxl (>=3.0.0) ; extra == 'excel'
Requires-Dist: xlrd (>=2.0.0) ; extra == 'excel'
Provides-Extra: html
Requires-Dist: beautifulsoup4 (>=4.9.0) ; extra == 'html'
Requires-Dist: lxml (>=4.6.0) ; extra == 'html'
Provides-Extra: office
Requires-Dist: python-docx (>=0.8.11) ; extra == 'office'
Requires-Dist: docx2txt (>=0.8) ; extra == 'office'
Requires-Dist: openpyxl (>=3.0.0) ; extra == 'office'
Requires-Dist: xlrd (>=2.0.0) ; extra == 'office'
Requires-Dist: python-pptx (>=0.6.0) ; extra == 'office'
Requires-Dist: odfpy (>=1.4.0) ; extra == 'office'
Requires-Dist: striprtf (>=0.0.10) ; extra == 'office'
Requires-Dist: beautifulsoup4 (>=4.9.0) ; extra == 'office'
Requires-Dist: lxml (>=4.6.0) ; extra == 'office'
Provides-Extra: opendocument
Requires-Dist: odfpy (>=1.4.0) ; extra == 'opendocument'
Provides-Extra: pdf
Requires-Dist: PyMuPDF (>=1.21.0) ; extra == 'pdf'
Requires-Dist: PyPDF2 (>=3.0.0) ; extra == 'pdf'
Requires-Dist: pdfplumber (>=0.7.0) ; extra == 'pdf'
Provides-Extra: powerpoint
Requires-Dist: python-pptx (>=0.6.0) ; extra == 'powerpoint'
Provides-Extra: rtf
Requires-Dist: striprtf (>=0.0.10) ; extra == 'rtf'
